justdd/__init__.py
justdd/__main__.py
justdd/app.py
justdd/constants.py
justdd/gui/__init__.py
justdd/gui/about_widget.py
justdd/gui/icons.py
justdd/gui/logs_window.py
justdd/gui/main_window.py
justdd/gui/pages.py
justdd/gui/step_card.py
justdd/logic/__init__.py
justdd/logic/flash_job.py
justdd/logic/flash_worker.py
justdd/logic/iso_detector.py
justdd/logic/logs.py
justdd/logic/message_utils.py
justdd/logic/steps.py
justdd/logic/utils.py
justdd-0.1.5.post2.dist-info/licenses/LICENSE
tests/smoke_test.py
justdd-0.1.5.post2.dist-info/METADATA
justdd-0.1.5.post2.dist-info/WHEEL
justdd-0.1.5.post2.dist-info/entry_points.txt
justdd-0.1.5.post2.dist-info/top_level.txt
justdd-0.1.5.post2.dist-info/RECORD
