Metadata-Version: 2.4
Name: justdd
Version: 0.1.5.post2
Summary: A simple, open-source tool to write Linux and Windows ISO images to USB drives.
Author: xxanqw
Maintainer-email: Ivan Potiienko <contact@xxanqw.pp.ua>
License-Expression: GPL-3.0-or-later
Project-URL: Homepage, https://github.com/xxanqw/justdd
Keywords: usb,dd,iso,image-writer,flashing,justdd
Classifier: Programming Language :: Python :: 3
Classifier: Programming Language :: Python :: 3.9
Classifier: Programming Language :: Python :: 3.10
Classifier: Programming Language :: Python :: 3.11
Classifier: Programming Language :: Python :: 3.12
Classifier: Programming Language :: Python :: 3.13
Classifier: Operating System :: OS Independent
Classifier: Topic :: Utilities
Classifier: Environment :: X11 Applications :: Qt
Requires-Python: <3.14,>=3.9
License-File: LICENSE
Requires-Dist: pyside6
Requires-Dist: requests
Requires-Dist: beautifulsoup4
Requires-Dist: desktop-notifier
Requires-Dist: aiohttp
Requires-Dist: qtawesome
Provides-Extra: dev
Requires-Dist: pyinstaller; extra == "dev"
Dynamic: license-file
